circle_detection_sdk/__init__.py
circle_detection_sdk/main.py
circle_detection_sdk/models/best1.pt
circle_detection_hough-1.0.2.dist-info/METADATA
circle_detection_hough-1.0.2.dist-info/WHEEL
circle_detection_hough-1.0.2.dist-info/entry_points.txt
circle_detection_hough-1.0.2.dist-info/top_level.txt
circle_detection_hough-1.0.2.dist-info/RECORD
