Metadata-Version: 2.4
Name: circle-detection-hough
Version: 1.0.2
Summary: 基于改进的Hough变换和YOLO目标检测的圆形检测SDK
Home-page: https://github.com/ruantong/circle-detection-hough
Author: ruantong
Author-email: ypwucu@isoftstone.com
Project-URL: Bug Reports, https://github.com/ruantong/circle-detection-hough/issues
Project-URL: Source, https://github.com/ruantong/circle-detection-hough
Project-URL: Documentation, https://circle-detection-hough.readthedocs.io/
Keywords: computer vision,circle detection,hough transform,yolo,object detection,image processing,machine learning,deep learning
Classifier: Development Status :: 4 - Beta
Classifier: Intended Audience :: Developers
Classifier: Intended Audience :: Science/Research
Classifier: License :: OSI Approved :: MIT License
Classifier: Operating System :: OS Independent
Classifier: Programming Language :: Python :: 3
Classifier: Programming Language :: Python :: 3.7
Classifier: Programming Language :: Python :: 3.8
Classifier: Programming Language :: Python :: 3.9
Classifier: Programming Language :: Python :: 3.10
Classifier: Programming Language :: Python :: 3.11
Classifier: Topic :: Scientific/Engineering :: Image Processing
Classifier: Topic :: Scientific/Engineering :: Artificial Intelligence
Classifier: Topic :: Software Development :: Libraries :: Python Modules
Requires-Python: >=3.7
Requires-Dist: opencv-python>=4.5.0
Requires-Dist: numpy>=1.19.0
Requires-Dist: matplotlib>=3.3.0
Requires-Dist: scipy>=1.6.0
Requires-Dist: torch>=1.9.0
Requires-Dist: ultralytics>=8.0.0
Requires-Dist: pathlib2>=2.3.0; python_version < "3.4"
Provides-Extra: dev
Requires-Dist: pytest>=6.0; extra == "dev"
Requires-Dist: pytest-cov>=2.0; extra == "dev"
Requires-Dist: black>=21.0; extra == "dev"
Requires-Dist: flake8>=3.8; extra == "dev"
Requires-Dist: mypy>=0.800; extra == "dev"
Provides-Extra: docs
Requires-Dist: sphinx>=4.0; extra == "docs"
Requires-Dist: sphinx-rtd-theme>=0.5; extra == "docs"
Dynamic: author
Dynamic: author-email
Dynamic: classifier
Dynamic: description
Dynamic: description-content-type
Dynamic: home-page
Dynamic: keywords
Dynamic: project-url
Dynamic: provides-extra
Dynamic: requires-dist
Dynamic: requires-python
Dynamic: summary
